README.rst
setup.py
AvgCpuTemp/__init__.py
AvgCpuTemp/avg_cpu_temp.py
CPU_temperature_monitor.egg-info/PKG-INFO
CPU_temperature_monitor.egg-info/SOURCES.txt
CPU_temperature_monitor.egg-info/dependency_links.txt
CPU_temperature_monitor.egg-info/entry_points.txt
CPU_temperature_monitor.egg-info/requires.txt
CPU_temperature_monitor.egg-info/top_level.txt