Metadata-Version: 2.1
Name: CPU-temperature-monitor
Version: 0.2
Summary: Script for checking current CPU temperature or average temperature in given time period.
Home-page: https://github.com/urosjevremovic/CPU_temperature_checker
Author: Uros Jevremovic
Author-email: jevremovic.uros91@gmail.com
License: MIT
Platform: UNKNOWN
